[
    {
        "module": "[lib]\\c_w.l",
        "size": {
            ".text": 15011,
            ".data": 20,
            ".bss": 348,
            ".text-delta": 0,
            ".data-delta": 0,
            ".bss-delta": 0
        }
    },
    {
        "module": "[lib]\\fz_wm.l",
        "size": {
            ".text": 2440,
            ".data": 0,
            ".bss": 0,
            ".text-delta": 0,
            ".data-delta": 0,
            ".bss-delta": 0
        }
    },
    {
        "module": "[lib]\\libcppabi_w.l",
        "size": {
            ".text": 44,
            ".data": 0,
            ".bss": 0,
            ".text-delta": 0,
            ".data-delta": 0,
            ".bss-delta": 0
        }
    },
    {
        "module": "[lib]\\m_wm.l",
        "size": {
            ".text": 802,
            ".data": 0,
            ".bss": 0,
            ".text-delta": 0,
            ".data-delta": 0,
            ".bss-delta": 0
        }
    },
    {
        "module": "anon$$obj.o",
        "size": {
            ".text": 32,
            ".data": 0,
            ".bss": 1280,
            ".text-delta": 0,
            ".data-delta": 0,
            ".bss-delta": 0
        }
    },
    {
        "module": "main.o",
        "size": {
            ".text": 2608,
            ".data": 16,
            ".bss": 1661,
            ".text-delta": 0,
            ".data-delta": 0,
            ".bss-delta": 0
        }
    },
    {
        "module": "mbed-os\\components",
        "size": {
            ".text": 169,
            ".data": 0,
            ".bss": 0,
            ".text-delta": 0,
            ".data-delta": 0,
            ".bss-delta": 0
        }
    },
    {
        "module": "mbed-os\\drivers",
        "size": {
            ".text": 2849,
            ".data": 0,
            ".bss": 0,
            ".text-delta": 0,
            ".data-delta": 0,
            ".bss-delta": 0
        }
    },
    {
        "module": "mbed-os\\features",
        "size": {
            ".text": 18,
            ".data": 0,
            ".bss": 0,
            ".text-delta": 0,
            ".data-delta": 0,
            ".bss-delta": 0
        }
    },
    {
        "module": "mbed-os\\hal",
        "size": {
            ".text": 2208,
            ".data": 4,
            ".bss": 66,
            ".text-delta": 0,
            ".data-delta": 0,
            ".bss-delta": 0
        }
    },
    {
        "module": "mbed-os\\platform",
        "size": {
            ".text": 7434,
            ".data": 64,
            ".bss": 253,
            ".text-delta": 0,
            ".data-delta": 0,
            ".bss-delta": 0
        }
    },
    {
        "module": "mbed-os\\rtos",
        "size": {
            ".text": 9676,
            ".data": 168,
            ".bss": 6754,
            ".text-delta": 0,
            ".data-delta": 0,
            ".bss-delta": 0
        }
    },
    {
        "module": "mbed-os\\targets",
        "size": {
            ".text": 11128,
            ".data": 4,
            ".bss": 948,
            ".text-delta": 0,
            ".data-delta": 0,
            ".bss-delta": 0
        }
    },
    {
        "module": "rotaryencoder\\RotaryEncoder.o",
        "size": {
            ".text": 582,
            ".data": 0,
            ".bss": 0,
            ".text-delta": 0,
            ".data-delta": 0,
            ".bss-delta": 0
        }
    },
    {
        "summary": {
            "static_ram": 11586,
            "static_ram_delta": 0,
            "total_flash": 55277,
            "total_flash_delta": 0
        }
    }
]
